django_migrations_plus-0.1.1.dist-info/metadata.json
django_migrations_plus-0.1.1.dist-info/RECORD
django_migrations_plus-0.1.1.dist-info/WHEEL
django_migrations_plus-0.1.1.dist-info/METADATA
django_migrations_plus-0.1.1.dist-info/top_level.txt
django_migrations_plus-0.1.1.dist-info/DESCRIPTION.rst
migrations_plus/tests.py
migrations_plus/operations.py
migrations_plus/__init__.py
migrations_plus/settings.py
