Metadata-Version: 2.0
Name: django-migrations-plus
Version: 0.1.1
Summary: Provides a method to run raw SQL in migrations with multiple databases
Home-page: UNKNOWN
Author: Diego Lorden
Author-email: diego.lorden@livelovely.com
License: MIT License
Platform: UNKNOWN
Classifier: Development Status :: 4 - Beta
Classifier: Framework :: Django
Classifier: Intended Audience :: Developers
Classifier: License :: OSI Approved :: MIT License
Classifier: Natural Language :: English
Classifier: Operating System :: OS Independent
Classifier: Programming Language :: Python :: 3.4
Classifier: Topic :: Database
